pgdrive/__init__.py
pgdrive/register.py
pgdrive/assets/PGDrive-large.png
pgdrive/assets/PGDrive.png
pgdrive/assets/maps/PGDrive-maps.json
pgdrive/assets/maps/README.md
pgdrive/assets/models/box.bam
pgdrive/assets/models/box.egg
pgdrive/assets/models/navi_arrow.gltf
pgdrive/assets/models/skybox.bam
pgdrive/assets/models/ferra/scene.bin
pgdrive/assets/models/ferra/scene.gltf
pgdrive/assets/models/ferra/textures/Material_002_baseColor.jpg
pgdrive/assets/models/ferra/textures/Material_002_normal.png
pgdrive/assets/models/ferra/textures/Material_003_baseColor.png
pgdrive/assets/models/ferra/textures/cuhk.jpg
pgdrive/assets/models/ferra/textures/dino_wheel_logo_001_baseColor.png
pgdrive/assets/models/ferra/textures/light_yellow_back_baseColor.jpg
pgdrive/assets/models/ferra/textures/lights_yellow_front_baseColor.jpg
pgdrive/assets/models/ferra/textures/lights_yellow_front_normal.png
pgdrive/assets/models/ferra/textures/logoFront_baseColor.jpg
pgdrive/assets/models/ferra/textures/seat_baseColor.jpg
pgdrive/assets/models/ferra/textures/wheel_001_baseColor.png
pgdrive/assets/models/ferra/textures/wheel_001_metallicRoughness.png
pgdrive/assets/models/new/130/scene.bin
pgdrive/assets/models/new/130/scene.gltf
pgdrive/assets/models/new/130/textures/b_blue_baseColor.jpeg
pgdrive/assets/models/new/130/textures/b_pillar_baseColor.png
pgdrive/assets/models/new/130/textures/b_red_baseColor.jpeg
pgdrive/assets/models/new/130/textures/b_white_baseColor.jpeg
pgdrive/assets/models/new/130/textures/b_yellow_baseColor.jpeg
pgdrive/assets/models/new/130/textures/body2_baseColor.jpeg
pgdrive/assets/models/new/130/textures/body_baseColor.jpeg
pgdrive/assets/models/new/130/textures/doorknob_baseColor.png
pgdrive/assets/models/new/130/textures/duct_baseColor.png
pgdrive/assets/models/new/130/textures/duct_normal.png
pgdrive/assets/models/new/130/textures/lens_baseColor.png
pgdrive/assets/models/new/130/textures/lens_normal.png
pgdrive/assets/models/new/130/textures/logo_baseColor.png
pgdrive-0.1.2.dist-info/LICENSE.txt
pgdrive-0.1.2.dist-info/METADATA
pgdrive-0.1.2.dist-info/WHEEL
pgdrive-0.1.2.dist-info/top_level.txt
pgdrive-0.1.2.dist-info/RECORD
