Metadata-Version: 2.1
Name: pgdrive
Version: 0.1.2
Summary: An open-ended driving simulator with infinite scenes
Home-page: https://github.com/decisionforce/pgdrive
Author: PGDrive Team
Author-email: liquanyi@bupt.edu.cn, pengzh@ie.cuhk.edu.hk
License: Apache 2.0
Platform: UNKNOWN
Requires-Dist: gym
Requires-Dist: numpy (<=1.19.3)
Requires-Dist: matplotlib
Requires-Dist: pandas
Requires-Dist: pygame
Requires-Dist: yapf (==0.30.0)
Requires-Dist: seaborn
Requires-Dist: panda3d (~=1.10.8)
Requires-Dist: panda3d-gltf
Requires-Dist: panda3d-simplepbr
Requires-Dist: pillow
Requires-Dist: pytest
Requires-Dist: opencv-python-headless
